hexcalculator/__init__.py
hexcalculator/hex.py
hexcalculator/hex_calculator.py
hexcalculator-0.1.1.dist-info/METADATA
hexcalculator-0.1.1.dist-info/WHEEL
hexcalculator-0.1.1.dist-info/RECORD
